CHANGES.txt
LICENCE.txt
README.md
pyproject.toml
readthedocs.yml
setup.cfg
setup.py
tox.ini
doc/Makefile
doc/requirements.txt
doc/source/conf.py
doc/source/identifiers.rst
doc/source/index.rst
doc/source/overview.rst
src/identifiers/GS1_CP_Ranges.xml
src/identifiers/IBAN_Registry_Release_88_September_2020.csv
src/identifiers/ISBN_Ranges.xml
src/identifiers/ISO10383_MIC.csv
src/identifiers/__init__.py
src/identifiers/banking.py
src/identifiers/bookland.py
src/identifiers/convert_iban_registry.py
src/identifiers/euvatid.py
src/identifiers/finance.py
src/identifiers/gs1.py
src/identifiers/gs1utils.py
src/identifiers/ibanregistry.py
src/identifiers/ibanutils.py
src/identifiers/identifier.py
src/identifiers/isbnutils.py
src/identifiers/ismnutils.py
src/identifiers/luhn.py
src/identifiers/micutils.py
src/identifiers/version.py
src/identifiers.egg-info/PKG-INFO
src/identifiers.egg-info/SOURCES.txt
src/identifiers.egg-info/dependency_links.txt
src/identifiers.egg-info/requires.txt
src/identifiers.egg-info/top_level.txt
tests/test_banking.py
tests/test_bookland.py
tests/test_euvatid.py
tests/test_finance.py
tests/test_gs1.py
tests/test_identifier.py