Metadata-Version: 2.1
Name: identifiers
Version: 0.4.1
Summary: International Standard Identifiers
Home-page: https://github.com/mamrhein/identifiers
Author: Michael Amrhein
Author-email: michael@adrhinum.de
License: BSD
Keywords: identifier GS1 GLN GTIN SSCC GSIN ISBN ISMN ISSN BIC IBAN MIC ISIN VAT
Platform: all
Classifier: Development Status :: 5 - Production/Stable
Classifier: Intended Audience :: Developers
Classifier: License :: OSI Approved :: BSD License
Classifier: Operating System :: OS Independent
Classifier: Programming Language :: Python
Classifier: Programming Language :: Python :: 3
Classifier: Programming Language :: Python :: 3.6
Classifier: Programming Language :: Python :: 3.7
Classifier: Programming Language :: Python :: 3.8
Classifier: Programming Language :: Python :: 3.9
Classifier: Programming Language :: Python :: Implementation :: CPython
Classifier: Programming Language :: Python :: Implementation :: PyPy
Classifier: Topic :: Software Development
Classifier: Topic :: Software Development :: Libraries
Classifier: Topic :: Software Development :: Libraries :: Python Modules
Requires-Python: >=3.6
